cilroy/__init__.py
cilroy/__main__.py
cilroy/config.py
cilroy/controller/__init__.py
cilroy/controller/controller.py
cilroy/controller/parameters.py
cilroy/controller/params.py
cilroy/controller/state.py
cilroy/log.py
cilroy/messages.py
cilroy/metadata.py
cilroy/models.py
cilroy/post.py
cilroy/resources/__init__.py
cilroy/resources/config.yaml
cilroy/retry/__init__.py
cilroy/retry/backoff.py
cilroy/retry/base.py
cilroy/retry/simple.py
cilroy/schedulers/__init__.py
cilroy/schedulers/base.py
cilroy/schedulers/cron.py
cilroy/schedulers/interval.py
cilroy/schedulers/timetable.py
cilroy/server.py
cilroy/service.py
cilroy/status.py
cilroy/utils.py
cilroy-0.6.1.dist-info/entry_points.txt
cilroy-0.6.1.dist-info/LICENSE
cilroy-0.6.1.dist-info/WHEEL
cilroy-0.6.1.dist-info/METADATA
cilroy-0.6.1.dist-info/RECORD
